<?xml version="1.0" encoding="UTF-8"?>


<library>
  <deprecatedName value="DE_Baden-W+uertenberg_L+oerrach_WRb"/>
  <longName value="Bibliothek der Wissenschaftlichen Regionalbibliothek Lörrach"/>

  <template value="aDISWeb"/>
  <variable name="server" value="bsz.ibs-bw.de"/>
  <variable name="startparams" value="?service=direct/0/Home/$DirectLink&amp;sp=SOPAC19"/>

  <homepage value="http://www.dhbw-loerrach.de/bibliothek.html"/>
  <testing-search value="yes"/>
  <testing-account value="unknown"/>
  
</library>
