<?xml version="1.0" encoding="UTF-8"?>

<library>
  <longName value="Stadtbibliothek Delitzsch"/>
  <shortName value="Stb Delitzsch"/>

  <template value="bibliothecaplus"/>
  <variable name="urlaccount" value="http://kultur.delitzsch.de/Mein-Konto"/>	
  <variable name="urlsearch" value="http://kultur.delitzsch.de/Mediensuche/Erweiterte-Suche"/>


  <variable name="baseurl" value="http://kultur.delitzsch.de/webopac/"/>
  <variable name="DB" value="web_biblio"/>

  <homepage value="https://www.delitzsch.de/mein-delitzsch/freizeit-und-sport/bibliothek/"/>
  <testing-search value="yes"/>
  <testing-account value="unknown"/>
</library>
